scikit_bayes-0.1.2.dist-info/licenses/LICENSE
skbn/__init__.py
skbn/_version.py
skbn/ande.py
skbn/mixed_nb.py
skbn/tests/__init__.py
skbn/tests/test_ande.py
skbn/tests/test_ande_extended.py
skbn/tests/test_common.py
skbn/tests/test_mixed_nb.py
skbn/utils/__init__.py
skbn/utils/discovery.py
skbn/utils/tests/__init__.py
skbn/utils/tests/test_discovery.py
scikit_bayes-0.1.2.dist-info/METADATA
scikit_bayes-0.1.2.dist-info/WHEEL
scikit_bayes-0.1.2.dist-info/top_level.txt
scikit_bayes-0.1.2.dist-info/RECORD
