Metadata-Version: 2.4
Name: scikit-bayes
Version: 0.1.2
Summary: A Python package for AnDE classifiers.
Author-email: Pablo Torrijos <pablo.torrijos@uclm.es>
Project-URL: Homepage, https://github.com/ptorrijos99/scikit-bayes
Project-URL: Issues, https://github.com/ptorrijos99/scikit-bayes/issues
Classifier: Programming Language :: Python :: 3
Classifier: Programming Language :: Python :: 3.9
Classifier: Programming Language :: Python :: 3.10
Classifier: Programming Language :: Python :: 3.11
Classifier: Programming Language :: Python :: 3.12
Classifier: Programming Language :: Python :: 3.13
Classifier: License :: OSI Approved :: BSD License
Classifier: Operating System :: POSIX
Classifier: Operating System :: Unix
Classifier: Operating System :: MacOS
Classifier: Operating System :: Microsoft :: Windows
Requires-Python: >=3.9
License-File: LICENSE
Requires-Dist: scikit-learn>=1.4.2
Requires-Dist: pyyaml>=6.0
Requires-Dist: liac-arff>=2.5
Dynamic: license-file
